gpx_etl/__init__.py
gpx_etl/transform.py
gpx_etl/utils.py
gpx_etl-0.0.2.dist-info/LICENSE
gpx_etl-0.0.2.dist-info/METADATA
gpx_etl-0.0.2.dist-info/WHEEL
gpx_etl-0.0.2.dist-info/RECORD
