Metadata-Version: 2.1
Name: gpx-etl
Version: 0.0.2
Summary: Parse, transform, process and create statistics from gpx files.
License: Apache-2.0
Author: pakdelm
Author-email: mehrshad.pakdel@posteo.de
Requires-Python: >=3.9
Classifier: Development Status :: 2 - Pre-Alpha
Classifier: License :: OSI Approved :: Apache Software License
Classifier: Operating System :: OS Independent
Classifier: Programming Language :: Python :: 3
Classifier: Programming Language :: Python :: 3.9
Classifier: Programming Language :: Python :: 3.10
Classifier: Programming Language :: Python :: 3.11
Classifier: Programming Language :: Python :: 3.12
Requires-Dist: gpxpy (>=1.6.2,<2.0.0)
Requires-Dist: pandas (>=2.2.0,<3.0.0)
Requires-Dist: pyarrow (>=15.0.0,<16.0.0)
